xstruct.py
xstruct-1.3.4.dist-info/LICENSE
xstruct-1.3.4.dist-info/METADATA
xstruct-1.3.4.dist-info/WHEEL
xstruct-1.3.4.dist-info/top_level.txt
xstruct-1.3.4.dist-info/RECORD
